fms/__init__.py
fms/_version.py
fms/py.typed
fms/datasets/__init__.py
fms/datasets/arrow.py
fms/datasets/instructions.py
fms/datasets/text.py
fms/datasets/util.py
fms/distributed/__init__.py
fms/distributed/strategy.py
fms/distributed/tensorparallel.py
fms/models/__init__.py
fms/models/bamba.py
fms/models/gpt_bigcode.py
fms/models/granite.py
fms/models/granite_moe_hybrid.py
fms/models/llama.py
fms/models/llava_next.py
fms/models/mistral.py
fms/models/mixtral.py
fms/models/mpnet.py
fms/models/roberta.py
fms/models/siglip_vision.py
fms/models/hf/README.md
fms/models/hf/__init__.py
fms/models/hf/lm_head_mixins.py
fms/models/hf/modeling_hf_adapter.py
fms/models/hf/utils.py
fms/models/hf/config_utils/__init__.py
fms/models/hf/config_utils/config_registry.py
fms/models/hf/config_utils/config_utils_types.py
fms/models/hf/config_utils/param_builders.py
fms/models/hf/gpt_bigcode/__init__.py
fms/models/hf/gpt_bigcode/configuration_gpt_bigcode_hf.py
fms/models/hf/gpt_bigcode/modeling_gpt_bigcode_hf.py
fms/models/hf/granite/__init__.py
fms/models/hf/granite/configuration_granite_hf.py
fms/models/hf/granite/modeling_granite_hf.py
fms/models/hf/llama/__init__.py
fms/models/hf/llama/configuration_llama_hf.py
fms/models/hf/llama/modeling_llama_hf.py
fms/models/hf/mixtral/__init__.py
fms/models/hf/mixtral/configuration_mixtral_hf.py
fms/models/hf/mixtral/modeling_mixtral_hf.py
fms/models/hf/roberta/__init__.py
fms/models/hf/roberta/modeling_roberta_hf.py
fms/modules/__init__.py
fms/modules/attention.py
fms/modules/embedding.py
fms/modules/feedforward.py
fms/modules/head.py
fms/modules/layernorm.py
fms/modules/linear.py
fms/modules/positions.py
fms/modules/ssm.py
fms/modules/tp.py
fms/testing/__init__.py
fms/testing/comparison.py
fms/testing/_internal/__init__.py
fms/testing/_internal/model_test_suite.py
fms/testing/_internal/hf/__init__.py
fms/testing/_internal/hf/model_test_suite.py
fms/training/__init__.py
fms/training/optimizers.py
fms/training/plugins.py
fms/training/trainer.py
ibm_fms-1.6.0.dist-info/licenses/LICENSE
ibm_fms-1.6.0.dist-info/METADATA
ibm_fms-1.6.0.dist-info/WHEEL
ibm_fms-1.6.0.dist-info/top_level.txt
ibm_fms-1.6.0.dist-info/RECORD
