Metadata-Version: 2.4
Name: ibm-fms
Version: 1.6.0
Summary: Foundation Model Stack is a collection of components for development, inference, training, and tuning of foundation models leveraging PyTorch native components.
Author-email: Antoni Viros i Martin <aviros@ibm.com>, Davis Wertheimer <Davis.Wertheimer@ibm.com>, Joshua Rosenkranz <jmrosenk@us.ibm.com>, Raghu Kiran Ganti <rganti@us.ibm.com>
License: Apache-2.0
Project-URL: Homepage, https://github.com/foundation-model-stack/foundation-model-stack
Project-URL: Repository, https://github.com/foundation-model-stack/foundation-model-stack
Project-URL: Issues, https://github.com/foundation-model-stack/foundation-model-stack/issues
Keywords: ibm-fms
Classifier: Development Status :: 3 - Alpha
Classifier: Environment :: Console
Classifier: Intended Audience :: Developers
Classifier: Intended Audience :: Science/Research
Classifier: Operating System :: OS Independent
Classifier: Programming Language :: Python
Classifier: Programming Language :: Python :: 3
Classifier: Programming Language :: Python :: 3.12
Classifier: Topic :: Scientific/Engineering
Classifier: Topic :: Scientific/Engineering :: Artificial Intelligence
Classifier: Topic :: Software Development :: Testing
Classifier: Topic :: Software Development :: Testing :: Unit
Classifier: Topic :: Software Development :: Libraries :: Python Modules
Requires-Python: <3.13,>=3.11
License-File: LICENSE
Requires-Dist: torch>=2.5.1
Provides-Extra: hf
Requires-Dist: transformers==4.48.3; extra == "hf"
Provides-Extra: dev
Requires-Dist: mypy==1.15.0; extra == "dev"
Requires-Dist: mypy-extensions==1.0.0; extra == "dev"
Requires-Dist: pytest==8.3.4; extra == "dev"
Requires-Dist: sentencepiece==0.2.0; extra == "dev"
Requires-Dist: transformers==4.55.4; extra == "dev"
Requires-Dist: pyarrow-stubs==17.16; extra == "dev"
Requires-Dist: types-requests==2.32.0.20241016; extra == "dev"
Requires-Dist: lm_eval==0.4.7; extra == "dev"
Requires-Dist: peft==0.14.0; extra == "dev"
Dynamic: license-file
